{
  "hash": "5638eadc",
  "configHash": "b6f353ad",
  "lockfileHash": "bd4e7675",
  "browserHash": "f469053c",
  "optimized": {
    "vue": {
      "src": "../../../node_modules/vue/dist/vue.runtime.esm-bundler.js",
      "file": "vue.js",
      "fileHash": "f0a1197c",
      "needsInterop": false
    },
    "vitepress > @vue/devtools-api": {
      "src": "../../../node_modules/@vue/devtools-api/dist/index.js",
      "file": "vitepress___@vue_devtools-api.js",
      "fileHash": "027d3158",
      "needsInterop": false
    },
    "vitepress > @vueuse/core": {
      "src": "../../../node_modules/@vueuse/core/index.mjs",
      "file": "vitepress___@vueuse_core.js",
      "fileHash": "8ad016fb",
      "needsInterop": false
    }
  },
  "chunks": {
    "chunk-BM2MTCRR": {
      "file": "chunk-BM2MTCRR.js"
    }
  }
}